{
  "testresult": [
    {
      "id": "595aa58d-1f3d-4c99-9dd8-32da81de1bbe",
      "project": "99f77fd7-a7ca-45be-9372-1dc1efdfa429",
      "iteration": "347c1737-bdd3-44bc-bc62-9c5d210b9af0",
      "created": "2019-06-05T03:36:33.272Z",
      "predictions": [
        {
          "probability": 1,
          "tagId": "19ce839a-c751-4832-a23d-d5b37be35fa8",
          "tagName": "HunnyBunnyHandSanitizer"
        },
        {
          "probability": 5.12256237e-9,
          "tagId": "965b757f-046a-41fa-a939-569919be0ccf",
          "tagName": "niangniang"
        },
        {
          "probability": 1.00558428e-9,
          "tagId": "1837d4b4-a5e6-4322-801a-295b68f2ed88",
          "tagName": "OtherCup"
        },
        {
          "probability": 4.8441734e-10,
          "tagId": "47cb3458-5e87-44b0-beac-0360e7fc4fc7",
          "tagName": "StarbucksBrownCup"
        }
      ],
      "filename": "L1020142.JPG"
    },
    {
      "id": "5cafeabc-577d-457c-9316-6832d8fc166b",
      "project": "99f77fd7-a7ca-45be-9372-1dc1efdfa429",
      "iteration": "347c1737-bdd3-44bc-bc62-9c5d210b9af0",
      "created": "2019-06-05T03:36:38.396Z",
      "predictions": [
        {
          "probability": 0.9297053,
          "tagId": "47cb3458-5e87-44b0-beac-0360e7fc4fc7",
          "tagName": "StarbucksBrownCup"
        },
        {
          "probability": 0.07029469,
          "tagId": "1837d4b4-a5e6-4322-801a-295b68f2ed88",
          "tagName": "OtherCup"
        },
        {
          "probability": 3.23890337e-9,
          "tagId": "19ce839a-c751-4832-a23d-d5b37be35fa8",
          "tagName": "HunnyBunnyHandSanitizer"
        },
        {
          "probability": 3.01865477e-10,
          "tagId": "965b757f-046a-41fa-a939-569919be0ccf",
          "tagName": "niangniang"
        }
      ],
      "filename": "L1020274.JPG"
    },
    {
      "id": "7ef36dfe-ac11-4c31-b6f6-9f3eceeed4a9",
      "project": "99f77fd7-a7ca-45be-9372-1dc1efdfa429",
      "iteration": "347c1737-bdd3-44bc-bc62-9c5d210b9af0",
      "created": "2019-06-05T03:36:39.492Z",
      "predictions": [
        {
          "probability": 0.9998888,
          "tagId": "1837d4b4-a5e6-4322-801a-295b68f2ed88",
          "tagName": "OtherCup"
        },
        {
          "probability": 0.000111205751,
          "tagId": "47cb3458-5e87-44b0-beac-0360e7fc4fc7",
          "tagName": "StarbucksBrownCup"
        },
        {
          "probability": 4.70307238e-10,
          "tagId": "19ce839a-c751-4832-a23d-d5b37be35fa8",
          "tagName": "HunnyBunnyHandSanitizer"
        },
        {
          "probability": 2.70694456e-11,
          "tagId": "965b757f-046a-41fa-a939-569919be0ccf",
          "tagName": "niangniang"
        }
      ],
      "filename": "L1020310.JPG"
    },
    {
      "id": "b15c1a71-09b0-41d1-a254-5d3bebc814b4",
      "project": "99f77fd7-a7ca-45be-9372-1dc1efdfa429",
      "iteration": "20afe02e-f37e-4a85-b0ed-01a85821d647",
      "created": "2019-06-05T03:37:08.939Z",
      "predictions": [
        {
          "probability": 1,
          "tagId": "19ce839a-c751-4832-a23d-d5b37be35fa8",
          "tagName": "HunnyBunnyHandSanitizer"
        },
        {
          "probability": 5.12256237e-9,
          "tagId": "965b757f-046a-41fa-a939-569919be0ccf",
          "tagName": "niangniang"
        },
        {
          "probability": 1.00558428e-9,
          "tagId": "1837d4b4-a5e6-4322-801a-295b68f2ed88",
          "tagName": "OtherCup"
        },
        {
          "probability": 4.8441734e-10,
          "tagId": "47cb3458-5e87-44b0-beac-0360e7fc4fc7",
          "tagName": "StarbucksBrownCup"
        }
      ],
      "filename": "L1020142.JPG"
    },
    {
      "id": "14af09e3-172c-4939-9ead-0ab2e299fd7e",
      "project": "99f77fd7-a7ca-45be-9372-1dc1efdfa429",
      "iteration": "20afe02e-f37e-4a85-b0ed-01a85821d647",
      "created": "2019-06-05T03:37:10.081Z",
      "predictions": [
        {
          "probability": 0.9297053,
          "tagId": "47cb3458-5e87-44b0-beac-0360e7fc4fc7",
          "tagName": "StarbucksBrownCup"
        },
        {
          "probability": 0.07029469,
          "tagId": "1837d4b4-a5e6-4322-801a-295b68f2ed88",
          "tagName": "OtherCup"
        },
        {
          "probability": 3.23890337e-9,
          "tagId": "19ce839a-c751-4832-a23d-d5b37be35fa8",
          "tagName": "HunnyBunnyHandSanitizer"
        },
        {
          "probability": 3.01865477e-10,
          "tagId": "965b757f-046a-41fa-a939-569919be0ccf",
          "tagName": "niangniang"
        }
      ],
      "filename": "L1020274.JPG"
    },
    {
      "id": "ead20fb5-a229-4047-b987-7ce2c93a7c64",
      "project": "99f77fd7-a7ca-45be-9372-1dc1efdfa429",
      "iteration": "20afe02e-f37e-4a85-b0ed-01a85821d647",
      "created": "2019-06-05T03:37:11.273Z",
      "predictions": [
        {
          "probability": 0.9998888,
          "tagId": "1837d4b4-a5e6-4322-801a-295b68f2ed88",
          "tagName": "OtherCup"
        },
        {
          "probability": 0.000111205751,
          "tagId": "47cb3458-5e87-44b0-beac-0360e7fc4fc7",
          "tagName": "StarbucksBrownCup"
        },
        {
          "probability": 4.70307238e-10,
          "tagId": "19ce839a-c751-4832-a23d-d5b37be35fa8",
          "tagName": "HunnyBunnyHandSanitizer"
        },
        {
          "probability": 2.70694456e-11,
          "tagId": "965b757f-046a-41fa-a939-569919be0ccf",
          "tagName": "niangniang"
        }
      ],
      "filename": "L1020310.JPG"
    },
    {
      "id": "edc8929f-7fdf-4463-89dd-dd1b2e110e27",
      "project": "99f77fd7-a7ca-45be-9372-1dc1efdfa429",
      "iteration": "23614af4-751c-49dd-bfa0-59e300758c93",
      "created": "2019-06-05T04:08:39.277Z",
      "predictions": [
        {
          "probability": 1,
          "tagId": "5deb98c3-02bd-4f51-a272-c2a3922ebe23",
          "tagName": "HunnyBunnyHandSanitizer"
        },
        {
          "probability": 5.12256237e-9,
          "tagId": "a653d112-9d10-498b-bf88-58b5a43e91e5",
          "tagName": "niangniang"
        },
        {
          "probability": 1.00558428e-9,
          "tagId": "8425a75f-818f-4893-9255-8420488468a1",
          "tagName": "OtherCup"
        },
        {
          "probability": 4.8441734e-10,
          "tagId": "3e78cfb0-bef4-4c94-9358-f965daa7403e",
          "tagName": "StarbucksBrownCup"
        }
      ],
      "filename": "L1020142.JPG"
    },
    {
      "id": "88d32ed5-cac6-4b51-bd3e-f286d49f7334",
      "project": "99f77fd7-a7ca-45be-9372-1dc1efdfa429",
      "iteration": "23614af4-751c-49dd-bfa0-59e300758c93",
      "created": "2019-06-05T04:08:40.371Z",
      "predictions": [
        {
          "probability": 0.9297053,
          "tagId": "3e78cfb0-bef4-4c94-9358-f965daa7403e",
          "tagName": "StarbucksBrownCup"
        },
        {
          "probability": 0.07029469,
          "tagId": "8425a75f-818f-4893-9255-8420488468a1",
          "tagName": "OtherCup"
        },
        {
          "probability": 3.23890337e-9,
          "tagId": "5deb98c3-02bd-4f51-a272-c2a3922ebe23",
          "tagName": "HunnyBunnyHandSanitizer"
        },
        {
          "probability": 3.01865477e-10,
          "tagId": "a653d112-9d10-498b-bf88-58b5a43e91e5",
          "tagName": "niangniang"
        }
      ],
      "filename": "L1020274.JPG"
    },
    {
      "id": "92487c16-000e-4c0e-940b-cb31c6fb3ab8",
      "project": "99f77fd7-a7ca-45be-9372-1dc1efdfa429",
      "iteration": "23614af4-751c-49dd-bfa0-59e300758c93",
      "created": "2019-06-05T04:08:41.678Z",
      "predictions": [
        {
          "probability": 0.9998888,
          "tagId": "8425a75f-818f-4893-9255-8420488468a1",
          "tagName": "OtherCup"
        },
        {
          "probability": 0.000111205751,
          "tagId": "3e78cfb0-bef4-4c94-9358-f965daa7403e",
          "tagName": "StarbucksBrownCup"
        },
        {
          "probability": 4.70307238e-10,
          "tagId": "5deb98c3-02bd-4f51-a272-c2a3922ebe23",
          "tagName": "HunnyBunnyHandSanitizer"
        },
        {
          "probability": 2.70694456e-11,
          "tagId": "a653d112-9d10-498b-bf88-58b5a43e91e5",
          "tagName": "niangniang"
        }
      ],
      "filename": "L1020310.JPG"
    }
  ]
}